vegspec/__init__.py
vegspec/vegspec.py
vegspec-1.0.4.dist-info/LICENSE.md
vegspec-1.0.4.dist-info/METADATA
vegspec-1.0.4.dist-info/WHEEL
vegspec-1.0.4.dist-info/top_level.txt
vegspec-1.0.4.dist-info/RECORD
