Metadata-Version: 2.1
Name: vegspec
Version: 1.0.4
Summary: A compilation of vegetative spectral indices and transformations in Python
Home-page: http://github.com/kthorp/vegspec
Author: Dr. Kelly R. Thorp
Author-email: kelly.thorp@usda.gov
License: Public Domain
Project-URL: Source, http://github.com/kthorp/vegspec
Project-URL: Bug Tracker, http://github.com/kthorp/vegspec/issues
Classifier: Programming Language :: Python :: 3
Classifier: Operating System :: OS Independent
Requires-Python: >=3.9
License-File: LICENSE.md
Requires-Dist: matplotlib
Requires-Dist: numpy
Requires-Dist: pandas
Requires-Dist: scipy
